jsonway/__init__.py
jsonway/main_jsonway.py
jsonway/mainjsonway.py
jsonway-1.0.2.dist-info/LICENSE
jsonway-1.0.2.dist-info/METADATA
jsonway-1.0.2.dist-info/WHEEL
jsonway-1.0.2.dist-info/top_level.txt
jsonway-1.0.2.dist-info/RECORD
