Metadata-Version: 2.1
Name: jsonway
Version: 1.0.2
Summary: complete tool for the JSON
Home-page: https://github.com/umeshdhakar/sample-python-package
Author: Vishwanath
Author-email: justvishu91@gmail.com
License: UNKNOWN
Platform: UNKNOWN
Classifier: Programming Language :: Python :: 3
Classifier: License :: OSI Approved :: MIT License
Classifier: Operating System :: OS Independent
